{
  "users": [
    {
      "description": "user 1",
      "username": "ah_automation+PartnerAdmin@agiletransformation.com",
      "password": "Agile4me",
      "firstName": "Partner",
      "lastName": "Admin",
      "companyName": "Automation_CA_NewNavigation",
      "type": "PartnerAdmin"
    },
    {
      "description": "user 2",
      "username": "ah_automation+ui_companyadmin@agiletransformation.com",
      "password": "12345678",
      "firstName": "Company",
      "lastName": "Admin",
      "companyName": "Automation_CA (DO NOT USE)",
      "type": "CompanyAdmin"
    }
  ],
  "companies": [
    {
      "environment": "atqa",
      "id": "80"
    },
    {
      "environment": "preprod",
      "id": "80"
    },
    {
      "environment": "uat",
      "id": "80"
    }
  ]
}